ddcuimap/__init__.py
ddcuimap/configs/__init__.py
ddcuimap/configs/apis/__init__.py
ddcuimap/configs/apis/config_metamap_api.yaml
ddcuimap/configs/apis/config_pinecone_api.yaml
ddcuimap/configs/apis/config_umls_api.yaml
ddcuimap/configs/config.yaml
ddcuimap/configs/custom/de.yaml
ddcuimap/configs/custom/hydra_base.yaml
ddcuimap/configs/custom/pvd.yaml
ddcuimap/configs/custom/title_def.yaml
ddcuimap/configs/semantic_search/embeddings.yaml
ddcuimap/curation/__init__.py
ddcuimap/curation/check_cuis.py
ddcuimap/curation/create_dictionary_import_file.py
ddcuimap/curation/utils/__init__.py
ddcuimap/curation/utils/curation_functions.py
ddcuimap/curation/utils/dictionary_functions.py
ddcuimap/curation/utils/process_data_dictionary.py
ddcuimap/curation/utils/text_processing.py
ddcuimap/curation/utils/xlsx_formatting.py
ddcuimap/hydra_search/__init__.py
ddcuimap/hydra_search/batch_hydra_query_pipeline.py
ddcuimap/metamap/__init__.py
ddcuimap/metamap/batch_query_pipeline.py
ddcuimap/metamap/skr_web_api/__init__.py
ddcuimap/metamap/skr_web_api/casauth.py
ddcuimap/metamap/utils/__init__.py
ddcuimap/metamap/utils/api_connection.py
ddcuimap/metamap/utils/metamap_query_processing_functions.py
ddcuimap/semantic_search/__init__.py
ddcuimap/semantic_search/batch_hybrid_query_pipeline.py
ddcuimap/semantic_search/configure_umls_index/__init__.py
ddcuimap/semantic_search/configure_umls_index/select_embed_upsert_pipeline.py
ddcuimap/semantic_search/configure_umls_index/step1_select_umls_subset.py
ddcuimap/semantic_search/configure_umls_index/step2_embed_umls_subset.py
ddcuimap/semantic_search/configure_umls_index/step3_upsert_umls_subset.py
ddcuimap/semantic_search/resources/__init__.py
ddcuimap/semantic_search/resources/dict_umls_upsert_ids.pkl
ddcuimap/semantic_search/utils/__init__.py
ddcuimap/semantic_search/utils/api_connection.py
ddcuimap/semantic_search/utils/builders.py
ddcuimap/semantic_search/utils/checks.py
ddcuimap/semantic_search/utils/eval_measures.py
data_dictionary_cui_mapping-1.1.6.dist-info/METADATA
data_dictionary_cui_mapping-1.1.6.dist-info/WHEEL
data_dictionary_cui_mapping-1.1.6.dist-info/RECORD
