Metadata-Version: 2.1
Name: data-dictionary-cui-mapping
Version: 1.1.6
Summary: This package allows you to load in a data dictionary and map cuis to defined fields using either the UMLS API or MetaMap API from NLM, or a Semantic Search pipeline using Pinecone vector database.
Home-page: https://github.com/kevon217/data-dictionary-cui-mapping
License: MIT
Keywords: BRICS,curation,data dictionary,UMLS,MetaMap,Metathesaurus,CUI,concept unique identifier,NLM,PubMedBERT,pritamdeka,pritamdeka/PubMedBERT-mnli-snli-scinli-scitail-mednli-stsb,semantic search,Pinecone,embeddings,vector database
Author: Kevin Armengol
Author-email: kevin.armengol@gmail.com
Requires-Python: >=3.8.1,<4.0.0
Classifier: License :: OSI Approved :: MIT License
Classifier: Programming Language :: Python :: 3
Classifier: Programming Language :: Python :: 3.9
Classifier: Programming Language :: Python :: 3.10
Classifier: Programming Language :: Python :: 3.11
Requires-Dist: cchardet (>=2.1.7,<3.0.0)
Requires-Dist: coloredlogs (>=15.0.1,<16.0.0)
Requires-Dist: hydra-core (>=1.1.0)
Requires-Dist: omegaconf (==2.1.2)
Requires-Dist: openpyxl (>=3.0.10)
Requires-Dist: pandas (>=1.5.2)
Requires-Dist: pathlib (>=1.0.1,<2.0.0)
Requires-Dist: pinecone-client (>=2.2.1,<3.0.0)
Requires-Dist: python-dotenv (==0.21.1)
Requires-Dist: requests (>=2.28.1)
Requires-Dist: requests-html (>=0.10.0)
Requires-Dist: sentence-transformers (>=2.2.2,<3.0.0)
Requires-Dist: transformers (==4.18.0)
Project-URL: Repository, https://github.com/kevon217/data-dictionary-cui-mapping
